fifo/myFifo.vhd
library IEEE;
use IEEE.std_logic_1164.all;
use IEEE.numeric_std.all;
-- use IEEE.std_logic_arith.all;
-- use IEEE.std_logic_unsigned.all;

entity myFifo is
    port (
        data_in: in std_logic_vector(7 downto 0);
        wr: in std_logic;
        clk: in std_logic;
        rst: in std_logic;
        en: in std_logic;
        data_out: out std_logic_vector(7 downto 0);
        red: out std_logic
    );
end entity myFifo;


architecture Behavior of myFifo is
    signal wptr, rptr: unsigned(3 downto 0);
    type fifo is array(15 downto 0) of std_logic_vector(7 downto 0);
    signal mem: fifo;
    
begin

    process(clk, rst)
    begin
        if rst = '1' then
            wptr <= "0000";
            rptr <= "0000";
            red <= '0';

        elsif (clk'event and clk='1') then
            if (en='1') then
                if (wr='1') then -- write operation
                    if (wptr < "1111") then
                        mem(to_integer(wptr)) <= data_in;
                        wptr <= wptr + 1;
                    else
                        red <= '1'; -- mem full
                    end if; 
                else -- read operation
                    if (rptr < wptr) then
                        data_out <= mem(to_integer(rptr));
                        rptr <= rptr + 1;
                        red <= '0';
                    else
                        red <= '1'; -- mem empty
                        data_out <= "00000000";
                    end if;
                end if;
            end if;
        end if;
    end process;
end architecture Behavior;

fifo/myFifoTb.vhd
library IEEE;
use IEEE.std_logic_1164.all;
use IEEE.numeric_std.all;

entity myFifoTb is
end entity myFifoTb;

architecture rtl of myFifoTb is
    component myFifo
    port (
        data_in: in std_logic_vector(7 downto 0);
        wr: in std_logic;
        clk: in std_logic;
        rst: in std_logic;
        en: in std_logic;
        data_out: out std_logic_vector(7 downto 0);
        red: out std_logic
    );
    end component;

    -- stimulus signals - signals mapped to inputs of tested unit
    signal clk: std_logic := '0';
    signal rst: std_logic := '0';
    signal data_in, data_out: std_logic_vector(7 downto 0);
    signal wr, en, red: std_logic;
    
begin
    DUT: myFifo
    port map(
        clk => clk,
        rst => rst,
        wr => wr,
        en => en,
        red => red,
        data_in => data_in,
        data_out => data_out
    );

    clk_gen: process begin
        clk <= '0';
        wait for 250 ns;
        clk <= '1';
        wait for 250 ns;
    end process;

    STIM: process begin
        rst <= '1';
        wait for 1000 ns;

        rst <= '0';
        en <= '1';
        wr <= '1';
        data_in <= "11111111";
        wait for 500 ns;

        en <= '1';
        wr <= '1';
        data_in <= "10101011";
        wait for 500 ns;

        en <= '1';
        wr <= '1';
        data_in <= "11111111";
        wait for 500 ns;

        en <= '1';
        wr <= '1';
        data_in <= "11010101";
        wait for 500 ns;


        en <= '1';
        wr <= '0';
        wait for 500 ns;

        en <= '1';
        wr <= '0';
        wait for 500 ns;

        en <= '1';
        wr <= '0';
        wait for 500 ns;

        en <= '1';
        wr <= '0';
        wait for 500 ns;

        en <= '1';
        wr <= '0';
        wait for 500 ns;

        wait;
    end process;
    
end architecture rtl;

fifo/myFifoTb_wave.vcd
$date
  Sun Jan  7 21:30:07 2024
$end
$version
  GHDL v0
$end
$timescale
  1 fs
$end
$scope module standard $end
$upscope $end
$scope module std_logic_1164 $end
$upscope $end
$scope module numeric_std $end
$upscope $end
$scope module myfifotb $end
$var reg 1 ! clk $end
$var reg 1 " rst $end
$var reg 8 # data_in[7:0] $end
$var reg 8 $ data_out[7:0] $end
$var reg 1 % wr $end
$var reg 1 & en $end
$var reg 1 ' red $end
$scope module dut $end
$var reg 8 ( data_in[7:0] $end
$var reg 1 ) wr $end
$var reg 1 * clk $end
$var reg 1 + rst $end
$var reg 1 , en $end
$var reg 8 - data_out[7:0] $end
$var reg 1 . red $end
$var reg 4 / wptr[3:0] $end
$var reg 4 0 rptr[3:0] $end
$comment mem is not handled $end
$upscope $end
$upscope $end
$enddefinitions $end
#0
0!
1"
bUUUUUUUU #
bUUUUUUUU $
U%
U&
0'
bUUUUUUUU (
U)
0*
1+
U,
bUUUUUUUU -
0.
b0000 /
b0000 0
#250000000
1!
1*
#500000000
0!
0*
#750000000
1!
1*
#1000000000
0!
0"
b11111111 #
1%
1&
b11111111 (
1)
0*
0+
1,
#1250000000
1!
1*
b0001 /
#1500000000
0!
b10101011 #
b10101011 (
0*
#1750000000
1!
1*
b0010 /
#2000000000
0!
b11111111 #
b11111111 (
0*
#2250000000
1!
1*
b0011 /
#2500000000
0!
b11010101 #
b11010101 (
0*
#2750000000
1!
1*
b0100 /
#3000000000
0!
0%
0)
0*
#3250000000
1!
b11111111 $
1*
b11111111 -
b0001 0
#3500000000
0!
0*
#3750000000
1!
b10101011 $
1*
b10101011 -
b0010 0
#4000000000
0!
0*
#4250000000
1!
b11111111 $
1*
b11111111 -
b0011 0
#4500000000
0!
0*
#4750000000
1!
b11010101 $
1*
b11010101 -
b0100 0
#5000000000
0!
0*
#5250000000
1!
b00000000 $
1'
1*
b00000000 -
1.
